{
  "$id": "https://geojson.org/schema/Polygon.json",
  "$schema": "http://json-schema.org/draft-07/schema#",
  "properties": {
    "bbox": {
      "items": {
        "type": "number"
      },
      "minItems": 4,
      "type": "array"
    },
    "coordinates": {
      "items": {
        "items": {
          "items": {
            "type": "number"
          },
          "minItems": 2,
          "type": "array"
        },
        "minItems": 4,
        "type": "array"
      },
      "type": "array"
    },
    "type": {
      "enum": [
        "Polygon"
      ],
      "type": "string"
    }
  },
  "required": [
    "type",
    "coordinates"
  ],
  "title": "GeoJSON Polygon",
  "type": "object"
}
